pytest_boardfarm3/__init__.py
pytest_boardfarm3/boardfarm_fixtures.py
pytest_boardfarm3/boardfarm_plugin.py
pytest_boardfarm3/exceptions.py
pytest_boardfarm3/py.typed
pytest_boardfarm3/pytest_plugin.py
pytest_boardfarm3/configs/__init__.py
pytest_boardfarm3/configs/logging.json
pytest_boardfarm3/lib/__init__.py
pytest_boardfarm3/lib/argument_parser.py
pytest_boardfarm3/lib/html_report.py
pytest_boardfarm3/lib/test_logger.py
pytest_boardfarm3/lib/utils.py
pytest_boardfarm3-1.0.1.dist-info/entry_points.txt
pytest_boardfarm3-1.0.1.dist-info/licenses/LICENSE
pytest_boardfarm3-1.0.1.dist-info/WHEEL
pytest_boardfarm3-1.0.1.dist-info/METADATA
pytest_boardfarm3-1.0.1.dist-info/RECORD
